dot_to_object/__init__.py
dot_to_object/dot_to_object.py
dot_to_object-0.0.2.dist-info/LICENSE
dot_to_object-0.0.2.dist-info/METADATA
dot_to_object-0.0.2.dist-info/WHEEL
dot_to_object-0.0.2.dist-info/top_level.txt
dot_to_object-0.0.2.dist-info/RECORD
