Metadata-Version: 2.1
Name: dot-to-object
Version: 0.0.2
Summary: A module to return python objects from dot notation strings.
Home-page: https://github.com/enesdogan00/dot_to_object
Author: Enes Doğan
Author-email: enesdogan26@gmail.com
Classifier: Development Status :: 4 - Beta
Classifier: License :: OSI Approved :: MIT License
Classifier: Operating System :: OS Independent
License-File: LICENSE
Requires-Dist: setuptools (>=45.0)
